gozer_engine/__init__.py
gozer_engine/base.py
gozer_engine/engine.py
gozer_engine/gozer.py
gozer_engine/history.py
gozer_engine/network.py
gozer_engine/parser.py
gozer_engine/render.py
gozer_engine-0.1.4.dist-info/LICENSE
gozer_engine-0.1.4.dist-info/METADATA
gozer_engine-0.1.4.dist-info/WHEEL
gozer_engine-0.1.4.dist-info/top_level.txt
gozer_engine-0.1.4.dist-info/RECORD
