Metadata-Version: 2.1
Name: gozer-engine
Version: 0.1.4
Summary: Browser engine for Gopher
Home-page: https://gitlab.com/schism15/gozer-engine
Author: schism
Author-email: schism@schism15.com
License: GPL v2
Keywords: gopher browser engine
Platform: UNKNOWN
Classifier: Programming Language :: Python :: 3
Classifier: License :: OSI Approved :: GNU General Public License v2 (GPLv2)
Classifier: Operating System :: POSIX :: Linux
Requires-Python: >=3.8
Requires-Dist: lark-parser
